k_amino/__init__.py
k_amino/py.typed
k_amino/k_async/__init__.py
k_amino/k_async/acm.py
k_amino/k_async/bot.py
k_amino/k_async/client.py
k_amino/k_async/local.py
k_amino/k_async/sockets.py
k_amino/k_sync/__init__.py
k_amino/k_sync/acm.py
k_amino/k_sync/bot.py
k_amino/k_sync/client.py
k_amino/k_sync/local.py
k_amino/k_sync/sockets.py
k_amino/lib/__init__.py
k_amino/lib/async_sessions.py
k_amino/lib/exception.py
k_amino/lib/headers.py
k_amino/lib/objects.py
k_amino/lib/sessions.py
k_amino/lib/types.py
k_amino/lib/util.py
k_amino.py-1.8.0.dist-info/LICENSE
k_amino.py-1.8.0.dist-info/METADATA
k_amino.py-1.8.0.dist-info/WHEEL
k_amino.py-1.8.0.dist-info/top_level.txt
k_amino.py-1.8.0.dist-info/RECORD
