Metadata-Version: 2.1
Name: k-amino.py
Version: 1.8.0
Summary: Amino Bots with python!
Home-page: https://github.com/kwel999/K_Amino
Author: KWEL
Author-email: itskwel999@gmail.com
License: Apache
Keywords: api,python,python3,python3.x,KWEL,kwel999,kwel.py,Amino,kamino,kamino pyK-Amino,kamino,kamino,kamino-bot,kamino-bots,kamino-bot,ndc,narvii.apps,aminoapps,kamino-py,kamino,kamino-bot,narvii
License-File: LICENSE
Requires-Dist: colorama
Requires-Dist: types-colorama
Requires-Dist: ujson
Requires-Dist: types-ujson
Requires-Dist: easy-events <=3.0.0
Requires-Dist: json-minify
Requires-Dist: python-socks[asyncio] >=2.4.0
Requires-Dist: httpx[socks] >=0.23.0
Requires-Dist: typing-extensions >=4.7.0
Requires-Dist: websockets >=12.0
